{
  "generatedAt": "2026-06-18T10:25:02.081Z",
  "brand": {
    "name": "Pulse",
    "tagline": "Real-time status for everything we run.",
    "primaryColor": "#22c55e",
    "website": "https://example.com",
    "supportUrl": "https://example.com/support"
  },
  "overall": "partial_outage",
  "totals": {
    "sites": 7,
    "up": 5,
    "down": 1,
    "degraded": 0,
    "paused": 1,
    "uptime": 0.9844
  },
  "groups": [
    {
      "id": "acme",
      "name": "Acme Inc",
      "icon": "🏢",
      "status": "partial_outage",
      "siteIds": [
        "acme-website",
        "acme-app",
        "acme-api",
        "acme-database"
      ]
    },
    {
      "id": "deps",
      "name": "Upstream Services",
      "icon": "🔌",
      "status": "operational",
      "siteIds": [
        "github-api",
        "wikipedia",
        "cloudflare"
      ]
    }
  ],
  "sites": [
    {
      "id": "acme-website",
      "name": "Acme Website",
      "url": "https://example.com",
      "group": "acme",
      "public": true,
      "status": "up",
      "responseTime": 200,
      "lastChecked": "2026-06-18T10:25:02.081Z",
      "uptime24h": 1,
      "uptime7d": 0.9973,
      "uptime30d": 0.9975,
      "uptime90d": 0.997,
      "avgResponse24h": 189,
      "spark": [
        "up",
        "up",
        "up",
        "up",
        "up",
        "up",
        "up",
        "up",
        "up",
        "up",
        "up",
        "up",
        "up",
        "up",
        "up",
        "up",
        "up",
        "up",
        "up",
        "up",
        "up",
        "up",
        "up",
        "up",
        "up",
        "up",
        "up",
        "up",
        "up",
        "up",
        "up",
        "up",
        "up",
        "up",
        "up",
        "up",
        "up",
        "up",
        "up",
        "up",
        "up",
        "up",
        "up",
        "up",
        "up"
      ],
      "tags": [
        "marketing",
        "primary"
      ],
      "httpStatus": 200,
      "ssl": {
        "validTo": "2026-08-21T10:25:02.081Z",
        "daysRemaining": 64,
        "issuer": "Let's Encrypt",
        "subject": "example.com",
        "expiringSoon": false
      },
      "domain": {
        "expiresAt": "2027-01-14T10:25:02.081Z",
        "daysRemaining": 210,
        "registrar": "Cloudflare Registrar",
        "expiringSoon": false
      }
    },
    {
      "id": "acme-app",
      "name": "Acme App",
      "url": "https://example.org",
      "group": "acme",
      "public": true,
      "status": "down",
      "responseTime": null,
      "lastChecked": "2026-06-18T10:25:02.081Z",
      "uptime24h": 0.9273,
      "uptime7d": 0.9906,
      "uptime30d": 0.9959,
      "uptime90d": 0.9911,
      "avgResponse24h": 333,
      "spark": [
        "up",
        "up",
        "up",
        "up",
        "up",
        "up",
        "up",
        "up",
        "up",
        "up",
        "up",
        "up",
        "up",
        "up",
        "down",
        "up",
        "up",
        "up",
        "up",
        "up",
        "up",
        "up",
        "up",
        "up",
        "up",
        "up",
        "up",
        "up",
        "up",
        "up",
        "up",
        "up",
        "up",
        "up",
        "up",
        "up",
        "up",
        "down",
        "down",
        "down",
        "down",
        "down",
        "down",
        "down",
        "down"
      ],
      "error": "Connection timed out",
      "ssl": {
        "validTo": "2026-06-26T10:25:02.081Z",
        "daysRemaining": 8,
        "issuer": "Let's Encrypt",
        "subject": "example.org",
        "expiringSoon": true
      }
    },
    {
      "id": "acme-api",
      "name": "Acme API",
      "url": "https://example.net",
      "group": "acme",
      "public": false,
      "status": "up",
      "responseTime": 168,
      "lastChecked": "2026-06-18T10:25:02.081Z",
      "uptime24h": 0.9792,
      "uptime7d": 0.998,
      "uptime30d": 0.9907,
      "uptime90d": 0.9939,
      "avgResponse24h": 153,
      "spark": [
        "up",
        "up",
        "up",
        "up",
        "up",
        "up",
        "up",
        "up",
        "up",
        "up",
        "up",
        "up",
        "up",
        "up",
        "up",
        "up",
        "up",
        "up",
        "up",
        "up",
        "up",
        "up",
        "up",
        "up",
        "up",
        "up",
        "up",
        "up",
        "up",
        "degraded",
        "up",
        "up",
        "up",
        "up",
        "up",
        "up",
        "up",
        "up",
        "up",
        "up",
        "up",
        "up",
        "up",
        "up",
        "up"
      ],
      "httpStatus": 200,
      "ssl": {
        "validTo": "2026-07-07T10:25:02.081Z",
        "daysRemaining": 19,
        "issuer": "Let's Encrypt",
        "subject": "example.net",
        "expiringSoon": true
      }
    },
    {
      "id": "acme-database",
      "name": "Acme Database",
      "url": "example.com:443",
      "group": "acme",
      "public": false,
      "status": "up",
      "responseTime": 12,
      "lastChecked": "2026-06-18T10:25:02.081Z",
      "uptime24h": 1,
      "uptime7d": 0.9983,
      "uptime30d": 0.9977,
      "uptime90d": 0.9968,
      "avgResponse24h": 13,
      "spark": [
        "up",
        "up",
        "up",
        "up",
        "up",
        "up",
        "up",
        "up",
        "up",
        "up",
        "up",
        "up",
        "up",
        "up",
        "up",
        "up",
        "up",
        "up",
        "up",
        "up",
        "up",
        "up",
        "up",
        "up",
        "up",
        "up",
        "up",
        "up",
        "up",
        "up",
        "up",
        "up",
        "up",
        "up",
        "up",
        "up",
        "up",
        "up",
        "up",
        "up",
        "up",
        "up",
        "up",
        "up",
        "up"
      ]
    },
    {
      "id": "github-api",
      "name": "GitHub API",
      "url": "https://api.github.com",
      "group": "deps",
      "public": true,
      "status": "up",
      "responseTime": 104,
      "lastChecked": "2026-06-18T10:25:02.081Z",
      "uptime24h": 1,
      "uptime7d": 0.998,
      "uptime30d": 0.9972,
      "uptime90d": 0.9969,
      "avgResponse24h": 101,
      "spark": [
        "up",
        "up",
        "up",
        "up",
        "up",
        "up",
        "up",
        "up",
        "up",
        "up",
        "up",
        "up",
        "up",
        "up",
        "up",
        "up",
        "up",
        "up",
        "up",
        "up",
        "up",
        "up",
        "up",
        "up",
        "up",
        "up",
        "up",
        "up",
        "up",
        "up",
        "up",
        "up",
        "up",
        "up",
        "up",
        "up",
        "up",
        "up",
        "up",
        "up",
        "up",
        "up",
        "up",
        "up",
        "up"
      ],
      "httpStatus": 200,
      "ssl": {
        "validTo": "2026-08-27T10:25:02.081Z",
        "daysRemaining": 70,
        "issuer": "Let's Encrypt",
        "subject": "api.github.com",
        "expiringSoon": false
      }
    },
    {
      "id": "wikipedia",
      "name": "Wikipedia",
      "url": "https://www.wikipedia.org",
      "group": "deps",
      "public": true,
      "status": "up",
      "responseTime": 103,
      "lastChecked": "2026-06-18T10:25:02.081Z",
      "uptime24h": 1,
      "uptime7d": 0.9968,
      "uptime30d": 0.9971,
      "uptime90d": 0.9971,
      "avgResponse24h": 96,
      "spark": [
        "up",
        "up",
        "up",
        "up",
        "up",
        "up",
        "up",
        "up",
        "up",
        "up",
        "up",
        "up",
        "up",
        "up",
        "up",
        "up",
        "up",
        "up",
        "up",
        "up",
        "up",
        "up",
        "up",
        "up",
        "up",
        "up",
        "up",
        "up",
        "up",
        "up",
        "up",
        "up",
        "up",
        "up",
        "up",
        "up",
        "up",
        "up",
        "up",
        "up",
        "up",
        "up",
        "up",
        "up",
        "up"
      ],
      "httpStatus": 200,
      "ssl": {
        "validTo": "2026-08-12T10:25:02.081Z",
        "daysRemaining": 55,
        "issuer": "Let's Encrypt",
        "subject": "www.wikipedia.org",
        "expiringSoon": false
      }
    },
    {
      "id": "cloudflare",
      "name": "Cloudflare",
      "url": "https://www.cloudflare.com",
      "group": "deps",
      "public": true,
      "status": "up",
      "responseTime": null,
      "lastChecked": "2026-06-18T10:25:02.081Z",
      "uptime24h": 0.9965,
      "uptime7d": 0.9968,
      "uptime30d": 0.9977,
      "uptime90d": 0.9967,
      "avgResponse24h": 47,
      "spark": [
        "up",
        "up",
        "up",
        "up",
        "up",
        "up",
        "up",
        "up",
        "up",
        "up",
        "up",
        "up",
        "up",
        "up",
        "up",
        "up",
        "up",
        "up",
        "up",
        "up",
        "up",
        "up",
        "up",
        "up",
        "up",
        "up",
        "up",
        "up",
        "up",
        "up",
        "up",
        "up",
        "up",
        "up",
        "up",
        "up",
        "up",
        "up",
        "up",
        "up",
        "up",
        "up",
        "up",
        "up",
        "up"
      ],
      "paused": true,
      "httpStatus": 200,
      "ssl": {
        "validTo": "2026-09-16T10:25:02.081Z",
        "daysRemaining": 90,
        "issuer": "Let's Encrypt",
        "subject": "www.cloudflare.com",
        "expiringSoon": false
      },
      "domain": {
        "expiresAt": "2027-04-14T10:25:02.081Z",
        "daysRemaining": 300,
        "registrar": "Cloudflare Registrar",
        "expiringSoon": false
      }
    }
  ],
  "incidents": [
    {
      "id": "inc-acme-app-down-1",
      "siteId": "acme-app",
      "siteName": "Acme App",
      "type": "down",
      "state": "open",
      "title": "Acme App is unreachable",
      "detail": "Origin returning connection timeouts from all regions.",
      "startedAt": "2026-06-18T09:45:02.081Z",
      "updates": [
        {
          "at": "2026-06-18T09:47:02.081Z",
          "message": "Investigating elevated error rates."
        },
        {
          "at": "2026-06-18T10:05:02.081Z",
          "message": "Identified an upstream provider outage."
        }
      ]
    },
    {
      "id": "inc-acme-app-ssl-1",
      "siteId": "acme-app",
      "siteName": "Acme App",
      "type": "ssl_expiring",
      "state": "open",
      "title": "TLS certificate expires in 8 days",
      "detail": "Renew the certificate to avoid an outage.",
      "startedAt": "2026-06-16T10:25:02.081Z"
    },
    {
      "id": "inc-acme-api-degraded-1",
      "siteId": "acme-api",
      "siteName": "Acme API",
      "type": "degraded",
      "state": "resolved",
      "title": "Elevated response times on the API",
      "startedAt": "2026-06-15T10:25:02.081Z",
      "resolvedAt": "2026-06-15T11:37:02.081Z",
      "durationMs": 4320000
    },
    {
      "id": "inc-acme-website-down-1",
      "siteId": "acme-website",
      "siteName": "Acme Website",
      "type": "down",
      "state": "resolved",
      "title": "Brief outage during a deploy",
      "detail": "A bad release caused 5xx responses; rolled back.",
      "startedAt": "2026-06-07T10:25:02.081Z",
      "resolvedAt": "2026-06-07T10:34:02.081Z",
      "durationMs": 540000
    }
  ]
}